README.rst
confucius.py
setup.py
confucius.egg-info/PKG-INFO
confucius.egg-info/SOURCES.txt
confucius.egg-info/dependency_links.txt
confucius.egg-info/top_level.txt