Metadata-Version: 1.1
Name: confucius
Version: 1.0.1
Summary: An easy way to provide environ backed config in your projects.
Home-page: http://github.com/funkybob/confucius
Author: Curtis Maloney
Author-email: curtis@tinbrain.net
License: MIT
Platform: UNKNOWN
Classifier: License :: OSI Approved :: MIT License
Classifier: Programming Language :: Python
Classifier: Programming Language :: Python :: 3
Classifier: Programming Language :: Python :: 3.6
